fila/__init__.py
fila/runner.py
fila/runner_test.py
fila-0.0.2.dist-info/LICENSE
fila-0.0.2.dist-info/METADATA
fila-0.0.2.dist-info/WHEEL
fila-0.0.2.dist-info/top_level.txt
fila-0.0.2.dist-info/RECORD
