Metadata-Version: 2.1
Name: fila
Version: 0.0.2
Summary: UNKNOWN
Home-page: https://github.com/iminders/fila
Author: liuwen
Author-email: liuwen.w@qq.com
License: UNKNOWN
Platform: UNKNOWN
Classifier: Programming Language :: Python :: 3
Classifier: License :: OSI Approved :: MIT License
Classifier: Operating System :: OS Independent
Requires-Python: >=3
Requires-Dist: pandas (>=0.18.0)
Requires-Dist: requests (>=2.0.0)
Requires-Dist: lxml (>=3.8.0)
Requires-Dist: simplejson (>=3.16.0)
Requires-Dist: msgpack (>=0.5.6)
Requires-Dist: pyzmq (>=16.0.0)
Requires-Dist: numpy (==1.16.0)
Requires-Dist: pandas (==0.25.3)
Requires-Dist: beautifulsoup4
Requires-Dist: matplotlib (==3.1.3)
Requires-Dist: scipy
Requires-Dist: tushare
